MsTargetPeaker/MsTargetPeaker.cfg
MsTargetPeaker/MsTargetPeaker.py
MsTargetPeaker/MsTargetPeakerEnv.py
MsTargetPeaker/MsTargetReporter.py
MsTargetPeaker/__init__.py
MsTargetPeaker/mcts/MCTS_DPW.py
MsTargetPeaker/mcts/__init__.py
MsTargetPeaker/policy/MsTargetPeaker_env66_40-2.state_dict.pth
MsTargetPeaker/tmsqe/ChromatogramDB.py
MsTargetPeaker/tmsqe/PeakQualityEval.py
MsTargetPeaker/tmsqe/PeakQualityReport.py
MsTargetPeaker/tmsqe/QualityEncoder.py
MsTargetPeaker/tmsqe/__init__.py
MsTargetPeaker/tmsqe/encoder/quality_encoder_type1.pickle
MsTargetPeaker/tmsqe/encoder/quality_encoder_type2.pickle
MsTargetPeaker/tmsqe/encoder/quality_encoder_type3.pickle
MsTargetPeaker/utils/__init__.py
MsTargetPeaker/utils/check_chrom_tsv.py
MsTargetPeaker/utils/merge_peak_csv.py
MsTargetPeaker/utils/split_chrom_tsv.py
mstargetpeaker-0.3.5.dist-info/licenses/LICENSE
mstargetpeaker-0.3.5.dist-info/METADATA
mstargetpeaker-0.3.5.dist-info/WHEEL
mstargetpeaker-0.3.5.dist-info/entry_points.txt
mstargetpeaker-0.3.5.dist-info/top_level.txt
mstargetpeaker-0.3.5.dist-info/RECORD
