Metadata-Version: 2.4
Name: MsTargetPeaker
Version: 0.3.5
Summary: A peak-searching procedure to identify optimal chromatographic peak regions for peak integration.
Author-email: Chi Yang <chiyang@mail.cgu.edu.tw>
License-File: LICENSE
Requires-Dist: numpy<2
Requires-Dist: scipy
Requires-Dist: pandas
Requires-Dist: xlsxwriter
Requires-Dist: gymnasium
Requires-Dist: tqdm
Requires-Dist: matplotlib>=3.6.3
Requires-Dist: torch>=1.13
Dynamic: license-file
